{
    "Ar36": {
        "error": 0.0002437775158399744,
        "error_type": "",
        "fit": "previous",
        "references": [
            {
                "exclude": false,
                "record_id": "bu-FC-J-17601"
            }
        ],
        "value": 0.012289066110908898
    },
    "Ar37": {
        "error": 0.0049633098741346,
        "error_type": "",
        "fit": "previous",
        "references": [
            {
                "exclude": false,
                "record_id": "bu-FC-J-17601"
            }
        ],
        "value": 0.03558285287545716
    },
    "Ar38": {
        "error": 0.004449378101496217,
        "error_type": "",
        "fit": "previous",
        "references": [
            {
                "exclude": false,
                "record_id": "bu-FC-J-17601"
            }
        ],
        "value": 0.02232558686006618
    },
    "Ar39": {
        "error": 0.00905701511915944,
        "error_type": "",
        "fit": "previous",
        "references": [
            {
                "exclude": false,
                "record_id": "bu-FC-J-17601"
            }
        ],
        "value": 0.07407469765673676
    },
    "Ar40": {
        "error": 0.017251391034727344,
        "error_type": "",
        "fit": "previous",
        "references": [
            {
                "exclude": false,
                "record_id": "bu-FC-J-17601"
            }
        ],
        "value": 2.0004789960891394
    },
    "Ar41": {
        "error": 0.02195288210570946,
        "error_type": "",
        "fit": "previous",
        "references": [
            {
                "exclude": false,
                "record_id": "bu-FC-J-17601"
            }
        ],
        "value": 0.10478671013986601
    }
}