{
    "AX":{
        "error":0.0064252032,
        "error_type":"SEM",
        "filter_outliers_dict":{
            "filter_outliers":true,
            "iterations":1,
            "std_devs":2
        },
        "fit":"average",
        "value":0.0010541621
    },
    "CDD":{
        "error":0.0000263053,
        "error_type":"SEM",
        "filter_outliers_dict":{
            "filter_outliers":true,
            "iterations":1,
            "std_devs":10
        },
        "fit":"average",
        "value":0.0001405208
    },
    "H1":{
        "error":0.0064432716,
        "error_type":"SEM",
        "filter_outliers_dict":{
            "filter_outliers":true,
            "iterations":1,
            "std_devs":2
        },
        "fit":"average",
        "value":0.0045848375
    },
    "H2":{
        "error":0.0183114603,
        "error_type":"SEM",
        "filter_outliers_dict":{
            "filter_outliers":true,
            "iterations":1,
            "std_devs":2
        },
        "fit":"average",
        "value":0.0644447373
    },
    "L1":{
        "error":0.0025653576,
        "error_type":"SEM",
        "filter_outliers_dict":{
            "filter_outliers":true,
            "iterations":1,
            "std_devs":2
        },
        "fit":"average",
        "value":-0.0422599809
    },
    "L2":{
        "error":0.0067454985,
        "error_type":"SEM",
        "filter_outliers_dict":{
            "filter_outliers":true,
            "iterations":1,
            "std_devs":2
        },
        "fit":"average",
        "value":-0.0526509085
    }
}