{
    "Ar36":{
        "error":0.000597982,
        "error_type":"SEM",
        "filter_outliers_dict":{
            "filter_outliers":true,
            "iterations":1,
            "std_devs":2
        },
        "fit":"Linear",
        "value":0.0091134053
    },
    "Ar37":{
        "error":0.0201966753,
        "error_type":"SEM",
        "filter_outliers_dict":{
            "filter_outliers":true,
            "iterations":1,
            "std_devs":2
        },
        "fit":"linear",
        "value":0.0047006597
    },
    "Ar38":{
        "error":0.0129629311,
        "error_type":"SEM",
        "filter_outliers_dict":{
            "filter_outliers":true,
            "iterations":1,
            "std_devs":2
        },
        "fit":"linear",
        "value":0.0882978884
    },
    "Ar39":{
        "error":0.025260335,
        "error_type":"SEM",
        "filter_outliers_dict":{
            "filter_outliers":true,
            "iterations":1,
            "std_devs":2
        },
        "fit":"Linear",
        "value":6.5261477475
    },
    "Ar40":{
        "error":0.0403132754,
        "error_type":"SEM",
        "filter_outliers_dict":{
            "filter_outliers":true,
            "iterations":1,
            "std_devs":2
        },
        "fit":"Linear",
        "value":94.2691661061
    },
    "Ar41":{
        "error":0.0196288508,
        "error_type":"SEM",
        "filter_outliers_dict":{
            "filter_outliers":true,
            "iterations":1,
            "std_devs":2
        },
        "fit":"Average",
        "value":0.0952088122
    }
}