{
    "Ar36": {
        "error": 0.00021599313402391056,
        "error_type": "SEM",
        "filter_outliers_dict": {
            "filter_outliers": true,
            "iterations": 1,
            "std_devs": 3,
            "use_iqr_filtering": false,
            "use_standard_deviation_filtering": false
        },
        "fit": "linear",
        "fn": 399,
        "include_baseline_error": true,
        "n": 400,
        "outlier_excluded": [
            217
        ],
        "reviewed": true,
        "user_excluded": [],
        "value": 0.023667974944012606
    },
    "Ar37": {
        "error": 0.0031379423355726286,
        "error_type": "SEM",
        "filter_outliers_dict": {
            "filter_outliers": true,
            "iterations": 1,
            "std_devs": 3,
            "use_iqr_filtering": false,
            "use_standard_deviation_filtering": false
        },
        "fit": "linear",
        "fn": 398,
        "include_baseline_error": true,
        "n": 400,
        "outlier_excluded": [
            77,
            7
        ],
        "reviewed": true,
        "user_excluded": [],
        "value": 0.16818843160616276
    },
    "Ar38": {
        "error": 0.0027868423802131694,
        "error_type": "SEM",
        "filter_outliers_dict": {
            "filter_outliers": true,
            "iterations": 1,
            "std_devs": 3,
            "use_iqr_filtering": false,
            "use_standard_deviation_filtering": false
        },
        "fit": "linear",
        "fn": 398,
        "include_baseline_error": true,
        "n": 400,
        "outlier_excluded": [
            323,
            364
        ],
        "reviewed": true,
        "user_excluded": [],
        "value": 0.273697728143822
    },
    "Ar39": {
        "error": 0.006935184068245663,
        "error_type": "SEM",
        "filter_outliers_dict": {
            "filter_outliers": true,
            "iterations": 1,
            "std_devs": 3,
            "use_iqr_filtering": false,
            "use_standard_deviation_filtering": false
        },
        "fit": "linear",
        "fn": 398,
        "include_baseline_error": true,
        "n": 400,
        "outlier_excluded": [
            305,
            286
        ],
        "reviewed": true,
        "user_excluded": [],
        "value": 17.23914045325472
    },
    "Ar40": {
        "error": 0.015720563983595084,
        "error_type": "SEM",
        "filter_outliers_dict": {
            "filter_outliers": true,
            "iterations": 1,
            "std_devs": 3,
            "use_iqr_filtering": false,
            "use_standard_deviation_filtering": false
        },
        "fit": "cubic",
        "fn": 399,
        "include_baseline_error": true,
        "n": 400,
        "outlier_excluded": [
            135
        ],
        "reviewed": true,
        "user_excluded": [],
        "value": 9.466512689251283
    },
    "Ar41": {
        "error": 0.014525285765022364,
        "error_type": "SEM",
        "filter_outliers_dict": {
            "filter_outliers": true,
            "iterations": 1,
            "std_devs": 3
        },
        "fit": "average",
        "value": 0.2548859524564528
    }
}