{
    "AX": {
        "error": 0.00843028111583701,
        "error_type": "SEM",
        "filter_outliers_dict": {
            "filter_outliers": true,
            "iterations": 1,
            "std_devs": 3,
            "use_iqr_filtering": false,
            "use_standard_deviation_filtering": false
        },
        "fit": "average",
        "fn": 45,
        "include_baseline_error": false,
        "n": 45,
        "outlier_excluded": [],
        "reviewed": true,
        "user_excluded": [],
        "value": -0.038952673671560155
    },
    "CDD": {
        "error": 1.2638833801687749e-05,
        "error_type": "SEM",
        "filter_outliers_dict": {
            "filter_outliers": true,
            "iterations": 1,
            "std_devs": 10,
            "use_iqr_filtering": false,
            "use_standard_deviation_filtering": false
        },
        "fit": "average",
        "fn": 45,
        "include_baseline_error": false,
        "n": 45,
        "outlier_excluded": [],
        "reviewed": true,
        "user_excluded": [],
        "value": 6.902991380128596e-05
    },
    "H1": {
        "error": 0.006111276016659009,
        "error_type": "SEM",
        "filter_outliers_dict": {
            "filter_outliers": true,
            "iterations": 1,
            "std_devs": 3,
            "use_iqr_filtering": false,
            "use_standard_deviation_filtering": false
        },
        "fit": "average",
        "fn": 45,
        "include_baseline_error": false,
        "n": 45,
        "outlier_excluded": [],
        "reviewed": true,
        "user_excluded": [],
        "value": -0.006650681951497164
    },
    "H2": {
        "error": 0.04299126169304288,
        "error_type": "SEM",
        "filter_outliers_dict": {
            "filter_outliers": true,
            "iterations": 1,
            "std_devs": 3,
            "use_iqr_filtering": false,
            "use_standard_deviation_filtering": false
        },
        "fit": "average",
        "fn": 45,
        "include_baseline_error": false,
        "n": 45,
        "outlier_excluded": [],
        "reviewed": true,
        "user_excluded": [],
        "value": 0.3751212928081966
    },
    "L1": {
        "error": 0.0037187121963104287,
        "error_type": "SEM",
        "filter_outliers_dict": {
            "filter_outliers": true,
            "iterations": 1,
            "std_devs": 3,
            "use_iqr_filtering": false,
            "use_standard_deviation_filtering": false
        },
        "fit": "average",
        "fn": 45,
        "include_baseline_error": false,
        "n": 45,
        "outlier_excluded": [],
        "reviewed": true,
        "user_excluded": [],
        "value": 0.03635300792714891
    },
    "L2": {
        "error": 0.00454204330816973,
        "error_type": "SEM",
        "filter_outliers_dict": {
            "filter_outliers": true,
            "iterations": 1,
            "std_devs": 3
        },
        "fit": "average",
        "value": 0.005208119296383566
    }
}