{
    "Ar36": {
        "error": 0.0002444129635353681,
        "error_type": "",
        "fit": "previous",
        "references": [
            {
                "exclude": false,
                "record_id": "bu-FC-J-9077"
            }
        ],
        "value": 0.010325239606181208
    },
    "Ar37": {
        "error": 0.005051263590172254,
        "error_type": "",
        "fit": "previous",
        "references": [
            {
                "exclude": false,
                "record_id": "bu-FC-J-9077"
            }
        ],
        "value": 0.02866044186407151
    },
    "Ar38": {
        "error": 0.002403562049789591,
        "error_type": "",
        "fit": "previous",
        "references": [
            {
                "exclude": false,
                "record_id": "bu-FC-J-9077"
            }
        ],
        "value": 0.003798103243365873
    },
    "Ar39": {
        "error": 0.008754002427264077,
        "error_type": "",
        "fit": "previous",
        "references": [
            {
                "exclude": false,
                "record_id": "bu-FC-J-9077"
            }
        ],
        "value": 0.012701178598479551
    },
    "Ar40": {
        "error": 0.008175498621834058,
        "error_type": "",
        "fit": "previous",
        "references": [
            {
                "exclude": false,
                "record_id": "bu-FC-J-9077"
            }
        ],
        "value": 2.4910059333664436
    },
    "Ar41": {
        "error": 0.012860124774782258,
        "error_type": "",
        "fit": "previous",
        "references": [
            {
                "exclude": false,
                "record_id": "bu-FC-J-9077"
            }
        ],
        "value": 0.04347866986212524
    }
}