{
    "Ar36": {
        "error": 0.0003798528572189281,
        "error_type": "SEM",
        "filter_outliers_dict": {
            "filter_outliers": true,
            "iterations": 1,
            "std_devs": 3,
            "use_iqr_filtering": false,
            "use_standard_deviation_filtering": false
        },
        "fit": "linear",
        "fn": 90,
        "include_baseline_error": true,
        "n": 90,
        "outlier_excluded": [],
        "reviewed": true,
        "user_excluded": [],
        "value": 0.011738378161219915
    },
    "Ar37": {
        "error": 0.008484412999521055,
        "error_type": "SEM",
        "filter_outliers_dict": {
            "filter_outliers": true,
            "iterations": 1,
            "std_devs": 3,
            "use_iqr_filtering": false,
            "use_standard_deviation_filtering": false
        },
        "fit": "linear",
        "fn": 90,
        "include_baseline_error": true,
        "n": 90,
        "outlier_excluded": [],
        "reviewed": true,
        "user_excluded": [],
        "value": 0.30814297715635003
    },
    "Ar38": {
        "error": 0.007737691327363378,
        "error_type": "SEM",
        "filter_outliers_dict": {
            "filter_outliers": true,
            "iterations": 1,
            "std_devs": 3,
            "use_iqr_filtering": false,
            "use_standard_deviation_filtering": false
        },
        "fit": "linear",
        "fn": 90,
        "include_baseline_error": true,
        "n": 90,
        "outlier_excluded": [],
        "reviewed": true,
        "user_excluded": [],
        "value": 0.37796528483319985
    },
    "Ar39": {
        "error": 0.020805283942827237,
        "error_type": "SEM",
        "filter_outliers_dict": {
            "filter_outliers": true,
            "iterations": 1,
            "std_devs": 3,
            "use_iqr_filtering": false,
            "use_standard_deviation_filtering": false
        },
        "fit": "linear",
        "fn": 89,
        "include_baseline_error": true,
        "n": 90,
        "outlier_excluded": [
            10
        ],
        "reviewed": true,
        "user_excluded": [],
        "value": 23.968961767080888
    },
    "Ar40": {
        "error": 0.05758310328037214,
        "error_type": "SEM",
        "filter_outliers_dict": {
            "filter_outliers": true,
            "iterations": 1,
            "std_devs": 3,
            "use_iqr_filtering": false,
            "use_standard_deviation_filtering": false
        },
        "fit": "linear",
        "fn": 90,
        "include_baseline_error": true,
        "n": 90,
        "outlier_excluded": [],
        "reviewed": true,
        "user_excluded": [],
        "value": 420.4076096655602
    },
    "Ar41": {
        "error": 0.02926745944866407,
        "error_type": "SEM",
        "filter_outliers_dict": {
            "filter_outliers": true,
            "iterations": 1,
            "std_devs": 3
        },
        "fit": "average",
        "value": 0.36164172384104776
    }
}