{
    "Ar36": {
        "error": 0.0002997075292756403,
        "error_type": "SEM",
        "filter_outliers_dict": {
            "filter_outliers": true,
            "iterations": 1,
            "std_devs": 3,
            "use_iqr_filtering": false,
            "use_standard_deviation_filtering": false
        },
        "fit": "parabolic",
        "fn": 399,
        "include_baseline_error": true,
        "n": 400,
        "outlier_excluded": [
            348
        ],
        "reviewed": true,
        "user_excluded": [],
        "value": 0.016261721923435373
    },
    "Ar37": {
        "error": 0.003214466025729198,
        "error_type": "SEM",
        "filter_outliers_dict": {
            "filter_outliers": true,
            "iterations": 1,
            "std_devs": 3,
            "use_iqr_filtering": false,
            "use_standard_deviation_filtering": false
        },
        "fit": "linear",
        "fn": 398,
        "include_baseline_error": true,
        "n": 400,
        "outlier_excluded": [
            137,
            138
        ],
        "reviewed": true,
        "user_excluded": [],
        "value": 0.06366017620737748
    },
    "Ar38": {
        "error": 0.002889142577171287,
        "error_type": "SEM",
        "filter_outliers_dict": {
            "filter_outliers": true,
            "iterations": 1,
            "std_devs": 3,
            "use_iqr_filtering": false,
            "use_standard_deviation_filtering": false
        },
        "fit": "linear",
        "fn": 397,
        "include_baseline_error": true,
        "n": 400,
        "outlier_excluded": [
            16,
            17,
            178
        ],
        "reviewed": true,
        "user_excluded": [],
        "value": 0.1458884127302828
    },
    "Ar39": {
        "error": 0.006539766505953967,
        "error_type": "SEM",
        "filter_outliers_dict": {
            "filter_outliers": true,
            "iterations": 1,
            "std_devs": 3,
            "use_iqr_filtering": false,
            "use_standard_deviation_filtering": false
        },
        "fit": "linear",
        "fn": 398,
        "include_baseline_error": true,
        "n": 400,
        "outlier_excluded": [
            188,
            199
        ],
        "reviewed": true,
        "user_excluded": [],
        "value": 6.367388005011953
    },
    "Ar40": {
        "error": 0.010236543173380547,
        "error_type": "SEM",
        "filter_outliers_dict": {
            "filter_outliers": true,
            "iterations": 1,
            "std_devs": 3,
            "use_iqr_filtering": false,
            "use_standard_deviation_filtering": false
        },
        "fit": "parabolic",
        "fn": 399,
        "include_baseline_error": true,
        "n": 400,
        "outlier_excluded": [
            0
        ],
        "reviewed": true,
        "user_excluded": [],
        "value": 4.6485258387363455
    },
    "Ar41": {
        "error": 0.015266895463622573,
        "error_type": "SEM",
        "filter_outliers_dict": {
            "filter_outliers": true,
            "iterations": 1,
            "std_devs": 3
        },
        "fit": "average",
        "value": 0.30589423826785755
    }
}